{
	"wallpapers": [
	{
		"author": "Technologx",
		"url": "http://technologx.x10.bz/iconpacks/glass/awesome_smile.jpg",
		"name": " Awesome Smile",
		"thumbnail": "http://technologx.x10.bz/iconpacks/glass/previews/awesome_smile.jpg"
	},
	{
		"author": "Technologx",
		"url": "http://technologx.x10.bz/iconpacks/glass/beautiful__sunset.jpg",
		"name": "Beautiful Sunset",
		"thumbnail": "http://technologx.x10.bz/iconpacks/glass/previews/beautiful__sunset.jpg"
	},
	{
		"author": "Technologx",
		"url": "http://technologx.x10.bz/iconpacks/glass/dodge_charger.jpg",
		"name": "Dodge Charger",
		"thumbnail": "http://technologx.x10.bz/iconpacks/glass/previews/dodge_charger.jpg"
	},
	{
		"author": "Technologx",
		"url": "http://technologx.x10.bz/iconpacks/glass/lazy_day.jpg",
		"name": "Lazy Day",
		"thumbnail": "http://technologx.x10.bz/iconpacks/glass/previews/lazy_day.jpg"
	},
	{
		"author": "Technologx",
		"url": "http://technologx.x10.bz/iconpacks/glass/megan_fox_hd.jpg",
		"name": "Megan Fox",
		"thumbnail": "http://technologx.x10.bz/iconpacks/glass/previews/megan_fox_hd.jpg"
	},
	{
		"author": "Technologx",
		"url": "http://technologx.x10.bz/iconpacks/glass/monkey.jpg",
		"name": "Monkey",
		"thumbnail": "http://technologx.x10.bz/iconpacks/glass/previews/monkey.jpg"
	},
	{
		"author": "Technologx",
		"url": "http://technologx.x10.bz/iconpacks/glass/moon_light_night.jpg",
		"name": "Moonlight Night",
		"thumbnail": "http://technologx.x10.bz/iconpacks/glass/previews/moon_light_night.jpg"
	},
	{
		"author": "Technologx",
		"url": "http://technologx.x10.bz/iconpacks/glass/nature.jpg",
		"name": "Nature",
		"thumbnail": "http://technologx.x10.bz/iconpacks/glass/previews/nature.jpg"
	},
	{
		"author": "Technologx",
		"url": "http://technologx.x10.bz/iconpacks/glass/rainy_day.jpg",
		"name": "Rainy Day",
		"thumbnail": "http://technologx.x10.bz/iconpacks/glass/previews/rainy_day.jpg"
	},
	{
		"author": "Technologx",
		"url": "http://technologx.x10.bz/iconpacks/glass/red_moonlight.jpg",
		"name": "Red Moonlight",
		"thumbnail": "http://technologx.x10.bz/iconpacks/glass/previews/red_moonlight.jpg"
	},
	{
		"author": "Technologx",
		"url": "http://technologx.x10.bz/iconpacks/glass/toxic_girl.jpg",
		"name": "Toxic Girl",
		"thumbnail": "http://technologx.x10.bz/iconpacks/glass/previews/toxic_girl.jpg"
	},
	{
		"author": "Technologx",
		"url": "http://technologx.x10.bz/iconpacks/glass/malemodel.jpg",
		"name": "Male Model",
		"thumbnail": "http://technologx.x10.bz/iconpacks/glass/previews/malemodel.jpg"
	},
	{
		"author": "Technologx",
		"url": "http://technologx.x10.bz/iconpacks/glass/malemodel2.jpg",
		"name": "Male Model 2",
		"thumbnail": "http://technologx.x10.bz/iconpacks/glass/previews/malemodel2.jpg"
	},
	{
		"author": "Technologx",
		"url": "http://technologx.x10.bz/iconpacks/glass/malemodel3.jpg",
		"name": "Male Model 3",
		"thumbnail": "http://technologx.x10.bz/iconpacks/glass/previews/malemodel3.jpg"
	},
	{
		"author": "Technologx",
		"url": "http://technologx.x10.bz/iconpacks/glass/lion_furious.jpg",
		"name": "Lion Furious",
		"thumbnail": "http://technologx.x10.bz/iconpacks/glass/previews/lion_furious.jpg"
	}
 ]
}